{
    "Blocks": [
        {
            "HB_H": 0,
            "HB_L": 0,
            "K_H": {
                "av": 1,
                "av_i": -6000000,
                "cons": 1,
                "cont_max": 0,
                "cont_min": 0,
                "desc_not_gs": [
                ],
                "is_golden_section": false,
                "iv": 1,
                "iv_i": -6000000,
                "type": 0,
                "which_gs": 2
            },
            "K_L": {
                "av": 1,
                "av_i": -6000000,
                "cons": 1,
                "cont_max": -6000000,
                "cont_min": -6000000,
                "desc_not_gs": [
                ],
                "is_golden_section": false,
                "iv": 1,
                "iv_i": -6000000,
                "type": 0,
                "which_gs": 1
            },
            "L_HB_L": 0,
            "M_a": 5000,
            "M_b": 5051.537929,
            "S": 303.391546,
            "X": {
                "av": 0,
                "av_i": -6000000,
                "cons": 0,
                "cont_max": 0,
                "cont_min": 0,
                "desc_not_gs": [
                ],
                "is_golden_section": false,
                "iv": 0,
                "iv_i": -6000000,
                "type": 0,
                "which_gs": 0
            },
            "X_U_A": 100.52898,
            "X_U_F": -1.73205,
            "Z": 0,
            "a": 100,
            "alpha_A": {
                "av": 120,
                "av_i": -6000000,
                "cons": 100,
                "cont_max": -6000000,
                "cont_min": -6000000,
                "desc_not_gs": [
                ],
                "is_golden_section": false,
                "iv": 100,
                "iv_i": -6000000,
                "type": 0,
                "which_gs": 0
            },
            "alpha_F": {
                "av": 100,
                "av_i": -6000000,
                "cons": 120,
                "cont_max": -6000000,
                "cont_min": -6000000,
                "desc_not_gs": [
                ],
                "is_golden_section": false,
                "iv": 120,
                "iv_i": -6000000,
                "type": 0,
                "which_gs": 0
            },
            "b": 102.261031,
            "foremast": false,
            "funnel": false,
            "h": 3,
            "habitability": true,
            "is_hull": true,
            "mainmast": false,
            "pap": false,
            "sb_h": "",
            "sb_l": "",
            "titleblock": "Корпус",
            "wheelhause": false,
            "x_g": 49.69587,
            "z_g": 1.49441
        },
        {
            "HB_H": 1,
            "HB_L": 0,
            "K_H": {
                "av": 2.617999,
                "av_i": 3,
                "cons": 0,
                "cont_max": 0,
                "cont_min": 0,
                "desc_not_gs": [
                ],
                "is_golden_section": true,
                "iv": 2.617999,
                "iv_i": 3,
                "type": 2,
                "which_gs": 2
            },
            "K_L": {
                "av": 0.382,
                "av_i": 4,
                "cons": 0,
                "cont_max": -6000000,
                "cont_min": -6000000,
                "desc_not_gs": [
                ],
                "is_golden_section": true,
                "iv": 0.382,
                "iv_i": 4,
                "type": 2,
                "which_gs": 1
            },
            "L_HB_L": 0,
            "M_a": 729.62,
            "M_b": 725.534109,
            "S": 288.796881,
            "X": {
                "av": 20.95443299763286,
                "av_i": -6000000,
                "cons": 0,
                "cont_max": 100.529,
                "cont_min": -1.73205,
                "desc_not_gs": [
                ],
                "is_golden_section": false,
                "iv": 20.95443299763286,
                "iv_i": -6000000,
                "type": 1,
                "which_gs": 0
            },
            "X_U_A": 59.154432,
            "X_U_F": 23.813054,
            "Z": 3,
            "a": 38.2,
            "alpha_A": {
                "av": 70,
                "av_i": 0,
                "cons": 90,
                "cont_max": -6000000,
                "cont_min": -6000000,
                "desc_not_gs": [
                    70,
                    75,
                    80,
                    85
                ],
                "is_golden_section": false,
                "iv": 90,
                "iv_i": 0,
                "type": 0,
                "which_gs": 0
            },
            "alpha_F": {
                "av": 90,
                "av_i": 0,
                "cons": 0,
                "cont_max": -6000000,
                "cont_min": -6000000,
                "desc_not_gs": [
                    70,
                    75,
                    80,
                    85
                ],
                "is_golden_section": false,
                "iv": 70,
                "iv_i": 0,
                "type": 2,
                "which_gs": 0
            },
            "b": 35.341378,
            "foremast": false,
            "funnel": false,
            "h": 7.853997000000001,
            "habitability": true,
            "is_hull": false,
            "mainmast": false,
            "pap": true,
            "sb_h": "",
            "sb_l": "",
            "titleblock": "A",
            "wheelhause": true,
            "x_g": 40.741308,
            "z_g": 6.97788
        },
        {
            "HB_H": 1,
            "HB_L": 2,
            "K_H": {
                "av": 0.618,
                "av_i": 0,
                "cons": 0,
                "cont_max": 0,
                "cont_min": 0,
                "desc_not_gs": [
                ],
                "is_golden_section": true,
                "iv": 0.618,
                "iv_i": 0,
                "type": 2,
                "which_gs": 2
            },
            "K_L": {
                "av": 0.055999,
                "av_i": 0,
                "cons": 0,
                "cont_max": -6000000,
                "cont_min": -6000000,
                "desc_not_gs": [
                ],
                "is_golden_section": true,
                "iv": 0.055999,
                "iv_i": 0,
                "type": 2,
                "which_gs": 1
            },
            "L_HB_L": 0,
            "M_a": 15.67944,
            "M_b": 15.67944,
            "S": 10.382214,
            "X": {
                "av": 59.15443299763287,
                "av_i": -6000000,
                "cons": 0,
                "cont_max": 100.52898,
                "cont_min": -1.73205,
                "desc_not_gs": [
                ],
                "is_golden_section": false,
                "iv": 59.15443299763287,
                "iv_i": -6000000,
                "type": 1,
                "which_gs": 0
            },
            "X_U_A": 64.754332,
            "X_U_F": 59.154432,
            "Z": 3,
            "a": 5.5999,
            "alpha_A": {
                "av": 90,
                "av_i": -6000000,
                "cons": 90,
                "cont_max": -6000000,
                "cont_min": -6000000,
                "desc_not_gs": [
                ],
                "is_golden_section": false,
                "iv": 90,
                "iv_i": -6000000,
                "type": 0,
                "which_gs": 0
            },
            "alpha_F": {
                "av": 90,
                "av_i": -6000000,
                "cons": 90,
                "cont_max": -6000000,
                "cont_min": -6000000,
                "desc_not_gs": [
                ],
                "is_golden_section": false,
                "iv": 90,
                "iv_i": -6000000,
                "type": 0,
                "which_gs": 0
            },
            "b": 5.5999,
            "foremast": false,
            "funnel": false,
            "h": 1.854,
            "habitability": true,
            "is_hull": false,
            "mainmast": false,
            "pap": false,
            "sb_h": "",
            "sb_l": "",
            "titleblock": "B",
            "wheelhause": false,
            "x_g": 61.954382,
            "z_g": 3.927
        },
        {
            "HB_H": 1,
            "HB_L": 3,
            "K_H": {
                "av": 0.618,
                "av_i": 0,
                "cons": 0,
                "cont_max": 0,
                "cont_min": 0,
                "desc_not_gs": [
                ],
                "is_golden_section": true,
                "iv": 0.618,
                "iv_i": 0,
                "type": 2,
                "which_gs": 2
            },
            "K_L": {
                "av": 0.09,
                "av_i": 1,
                "cons": 0,
                "cont_max": -6000000,
                "cont_min": -6000000,
                "desc_not_gs": [
                ],
                "is_golden_section": true,
                "iv": 0.09,
                "iv_i": 1,
                "type": 2,
                "which_gs": 1
            },
            "L_HB_L": 0,
            "M_a": 40.5,
            "M_b": 36.152392,
            "S": 16.225486,
            "X": {
                "av": 64.75433299763287,
                "av_i": -6000000,
                "cons": 0,
                "cont_max": 100.52898,
                "cont_min": -1.73205,
                "desc_not_gs": [
                ],
                "is_golden_section": false,
                "iv": 64.75433299763287,
                "iv_i": -6000000,
                "type": 1,
                "which_gs": 0
            },
            "X_U_A": 73.257555,
            "X_U_F": 64.754332,
            "Z": 3,
            "a": 9,
            "alpha_A": {
                "av": 90,
                "av_i": 1,
                "cons": 0,
                "cont_max": -6000000,
                "cont_min": -6000000,
                "desc_not_gs": [
                    70,
                    75,
                    80,
                    85
                ],
                "is_golden_section": false,
                "iv": 75,
                "iv_i": 1,
                "type": 2,
                "which_gs": 0
            },
            "alpha_F": {
                "av": 75,
                "av_i": 1,
                "cons": 90,
                "cont_max": -6000000,
                "cont_min": -6000000,
                "desc_not_gs": [
                ],
                "is_golden_section": false,
                "iv": 90,
                "iv_i": 1,
                "type": 0,
                "which_gs": 0
            },
            "b": 8.503222,
            "foremast": false,
            "funnel": false,
            "h": 1.854,
            "habitability": true,
            "is_hull": false,
            "mainmast": false,
            "pap": false,
            "sb_h": "",
            "sb_l": "",
            "titleblock": "С",
            "wheelhause": false,
            "x_g": 69.133663,
            "z_g": 3.93577
        },
        {
            "HB_H": 2,
            "HB_L": 0,
            "K_H": {
                "av": 6.6,
                "av_i": 0,
                "cons": 6.6,
                "cont_max": 6.6,
                "cont_min": 5,
                "desc_not_gs": [
                ],
                "is_golden_section": false,
                "iv": 6.6,
                "iv_i": 0,
                "type": 1,
                "which_gs": 2
            },
            "K_L": {
                "av": 0.012,
                "av_i": 0,
                "cons": 0.012,
                "cont_max": -6000000,
                "cont_min": -6000000,
                "desc_not_gs": [
                ],
                "is_golden_section": true,
                "iv": 0.012,
                "iv_i": 0,
                "type": 0,
                "which_gs": 1
            },
            "L_HB_L": 0,
            "M_a": 0.72,
            "M_b": 0.719998,
            "S": 23.75999,
            "X": {
                "av": 49.93802939180864,
                "av_i": -6000000,
                "cons": 0,
                "cont_max": 59.1544,
                "cont_min": 23.8131,
                "desc_not_gs": [
                ],
                "is_golden_section": false,
                "iv": 49.93802939180864,
                "iv_i": -6000000,
                "type": 1,
                "which_gs": 0
            },
            "X_U_A": 51.138029,
            "X_U_F": 49.938029,
            "Z": 10.853997,
            "a": 1.2,
            "alpha_A": {
                "av": 90,
                "av_i": 1,
                "cons": 90,
                "cont_max": -6000000,
                "cont_min": -6000000,
                "desc_not_gs": [
                    80,
                    85,
                    90
                ],
                "is_golden_section": false,
                "iv": 90,
                "iv_i": 0,
                "type": 2,
                "which_gs": 0
            },
            "alpha_F": {
                "av": 90,
                "av_i": 0,
                "cons": 90,
                "cont_max": -6000000,
                "cont_min": -6000000,
                "desc_not_gs": [
                    80,
                    85,
                    90
                ],
                "is_golden_section": false,
                "iv": 90,
                "iv_i": 1,
                "type": 2,
                "which_gs": 0
            },
            "b": 1.199999,
            "foremast": true,
            "funnel": false,
            "h": 19.799999999999997,
            "habitability": false,
            "is_hull": false,
            "mainmast": false,
            "pap": false,
            "sb_h": "",
            "sb_l": "",
            "titleblock": "Фок-мачта",
            "wheelhause": false,
            "x_g": 50.538028,
            "z_g": 20.753998
        },
        {
            "HB_H": 4,
            "HB_L": 0,
            "K_H": {
                "av": 3.5,
                "av_i": -6000000,
                "cons": 3.5,
                "cont_max": 4,
                "cont_min": 2.7,
                "desc_not_gs": [
                ],
                "is_golden_section": false,
                "iv": 3.5,
                "iv_i": -6000000,
                "type": 1,
                "which_gs": 2
            },
            "K_L": {
                "av": 0.056,
                "av_i": -6000000,
                "cons": 0.056,
                "cont_max": -6000000,
                "cont_min": -6000000,
                "desc_not_gs": [
                ],
                "is_golden_section": false,
                "iv": 0.056,
                "iv_i": -6000000,
                "type": 0,
                "which_gs": 1
            },
            "L_HB_L": 0,
            "M_a": 15.68,
            "M_b": 6.603931,
            "S": 44.257158,
            "X": {
                "av": 64.754332,
                "av_i": -6000000,
                "cons": 0,
                "cont_max": 73.2576,
                "cont_min": 64.7543,
                "desc_not_gs": [
                ],
                "is_golden_section": false,
                "iv": 64.754332,
                "iv_i": -6000000,
                "type": 1,
                "which_gs": 0
            },
            "X_U_A": 68.502898,
            "X_U_F": 65.672962,
            "Z": 4.854,
            "a": 5.6000000000000005,
            "alpha_A": {
                "av": 85,
                "av_i": 1,
                "cons": 0,
                "cont_max": -6000000,
                "cont_min": -6000000,
                "desc_not_gs": [
                    80,
                    85,
                    90
                ],
                "is_golden_section": false,
                "iv": 80,
                "iv_i": 0,
                "type": 2,
                "which_gs": 0
            },
            "alpha_F": {
                "av": 80,
                "av_i": 0,
                "cons": 0,
                "cont_max": -6000000,
                "cont_min": -6000000,
                "desc_not_gs": [
                    80,
                    85,
                    90
                ],
                "is_golden_section": false,
                "iv": 85,
                "iv_i": 1,
                "type": 2,
                "which_gs": 0
            },
            "b": 2.829935,
            "foremast": false,
            "funnel": true,
            "h": 10.5,
            "habitability": false,
            "is_hull": false,
            "mainmast": false,
            "pap": false,
            "sb_h": "",
            "sb_l": "",
            "titleblock": "Труба",
            "wheelhause": false,
            "x_g": 67.39776,
            "z_g": 10.679047
        },
        {
            "HB_H": 3,
            "HB_L": 0,
            "K_H": {
                "av": 4,
                "av_i": -6000000,
                "cons": 4,
                "cont_max": 4,
                "cont_min": 1.7,
                "desc_not_gs": [
                ],
                "is_golden_section": false,
                "iv": 4,
                "iv_i": -6000000,
                "type": 1,
                "which_gs": 2
            },
            "K_L": {
                "av": 0.012,
                "av_i": -6000000,
                "cons": 0.012,
                "cont_max": -6000000,
                "cont_min": -6000000,
                "desc_not_gs": [
                ],
                "is_golden_section": false,
                "iv": 0.012,
                "iv_i": -6000000,
                "type": 0,
                "which_gs": 1
            },
            "L_HB_L": 0,
            "M_a": 0.72,
            "M_b": 0.719998,
            "S": 14.399994,
            "X": {
                "av": 59.154432,
                "av_i": -6000000,
                "cons": 0,
                "cont_max": 64.7543,
                "cont_min": 59.1544,
                "desc_not_gs": [
                ],
                "is_golden_section": false,
                "iv": 59.154432,
                "iv_i": -6000000,
                "type": 1,
                "which_gs": 0
            },
            "X_U_A": 60.354432,
            "X_U_F": 59.154432,
            "Z": 4.854,
            "a": 1.2,
            "alpha_A": {
                "av": 90,
                "av_i": 0,
                "cons": 90,
                "cont_max": -6000000,
                "cont_min": -6000000,
                "desc_not_gs": [
                    80,
                    85,
                    90
                ],
                "is_golden_section": false,
                "iv": 90,
                "iv_i": 0,
                "type": 2,
                "which_gs": 0
            },
            "alpha_F": {
                "av": 90,
                "av_i": 0,
                "cons": 90,
                "cont_max": -6000000,
                "cont_min": -6000000,
                "desc_not_gs": [
                    80,
                    85,
                    90
                ],
                "is_golden_section": false,
                "iv": 90,
                "iv_i": 0,
                "type": 2,
                "which_gs": 0
            },
            "b": 1.199999,
            "foremast": false,
            "funnel": false,
            "h": 12,
            "habitability": false,
            "is_hull": false,
            "mainmast": true,
            "pap": false,
            "sb_h": "",
            "sb_l": "",
            "titleblock": "Грот-мачта",
            "wheelhause": false,
            "x_g": 59.754431,
            "z_g": 10.854
        }
    ],
    "General": {
        "calc": {
            "ECB": 1118.5995710132738,
            "FB": 3,
            "GS_H": [
                0.618,
                1,
                1.617999,
                2.617999
            ],
            "GS_L": [
                0.055999,
                0.09,
                0.146,
                0.236,
                0.382,
                0.618,
                1
            ],
            "L_V_max": 200,
            "cn": [
                3,
                0.287,
                -0.00308,
                2.8000000000000003e-06
            ],
            "p": 0.7000000000000001,
            "q": 50,
            "t": 7
        },
        "user": {
            "B": 12.5,
            "D": 2000,
            "GM": 1.25,
            "H": 6.5,
            "L": 100,
            "T": 3.2,
            "delta": 0.5,
            "k_DS": 0.8,
            "p_": 0.1,
            "p_w": 1200,
            "project_name": "EPLS",
            "q_": 0.5,
            "t_": 10,
            "theta": 15
        }
    }
}
